[
    {
        "name": "simplebar",
        "pageName": "Simple Bar Chart",     
        "script": "examples/barchart.js",
        "imageUrl": "images/barchart.PNG",
        "partial": "examples/partials/example.html",
        "partialCSS": "examples/css/simpleBar.css"
    }, 
    {
        "name": "zoomableBar",
        "pageName": "Zoomable Bar Chart", 
        "script": "examples/zoomableBar.js",
        "imageUrl": "images/zoomableBar.PNG",
        "partial": "examples/partials/example.html",
        "partialCSS": "examples/css/example.css"
    },
    {
        "name": "stackedGroupedBar",
        "pageName": "Stacked & Grouped Bar Chart", 
        "script": "examples/stackedBar.js",
        "imageUrl": "images/stackedBar.PNG",
        "partial": "examples/partials/example.html",
        "partialCSS": "examples/css/example.css"
    },
    {
        "name": "rangeTarget",
        "pageName": "Ranges & Targets", 
        "script": "examples/rangeTarget.js",
        "imageUrl": "images/rangeTarget.PNG",
        "partial": "examples/partials/example.html",
        "partialCSS": "examples/css/example.css"
    },
    {
        "name": "stackedWithTarget",
        "pageName": "Stacked Bar with Target", 
        "script": "examples/targets.js",
        "imageUrl": "images/stackedTarget.PNG",
        "partial": "examples/partials/example.html",
        "partialCSS": "examples/css/example.css"
    },
    {
        "name": "Dataset",
        "pageName": "Crossfiltered Charts", 
        "script": "examples/dataset.js",
        "imageUrl": "images/crossfilter.PNG",
        "partial": "examples/partials/dataset.html",
        "partialCSS": "examples/css/example.css"
    }
]